stream_source/__init__.py
stream_source/bq_stream_data_source.py
stream_source/bq_stream_reader.py
stream_source/test.py
streaming_connector/__init__.py
streaming_connector/bq_stream_register.py
bigquery_spark_streaming_connector-0.7.0.dist-info/METADATA
bigquery_spark_streaming_connector-0.7.0.dist-info/WHEEL
bigquery_spark_streaming_connector-0.7.0.dist-info/entry_points.txt
bigquery_spark_streaming_connector-0.7.0.dist-info/top_level.txt
bigquery_spark_streaming_connector-0.7.0.dist-info/RECORD
