Metadata-Version: 2.1
Name: bigquery-spark-streaming-connector
Version: 0.7.0
Summary: spark structured streaming connector utility for gcp bigquery using storage api services.
Author-email: Indranil Tarafdar <indranil.tarafdar@databricks.com>
Requires-Dist: google-cloud-bigquery-storage ==2.25.0
Requires-Dist: google-cloud-bigquery[fastavro]
Requires-Dist: pyarrow
Requires-Dist: fastavro
